{
    "_links": {
        "self": {
            "href": "http:\/\/default\/taxonomy\/term\/17?_format=hal_json"
        },
        "type": {
            "href": "http:\/\/drupal.org\/rest\/type\/taxonomy_term\/position"
        }
    },
    "tid": [
        {
            "value": 17
        }
    ],
    "uuid": [
        {
            "value": "dcc48931-da3b-4af8-91dd-478c845298cf"
        }
    ],
    "langcode": [
        {
            "value": "en",
            "lang": "en"
        }
    ],
    "vid": [
        {
            "target_id": "position"
        }
    ],
    "name": [
        {
            "value": "Coordinating Professor",
            "lang": "en"
        }
    ],
    "weight": [
        {
            "value": 0
        }
    ],
    "changed": [
        {
            "value": 1514377152,
            "lang": "en"
        }
    ],
    "default_langcode": [
        {
            "value": true,
            "lang": "en"
        }
    ],
    "metatag": [
        {
            "value": {
                "title": "Coordinating Professor | InED",
                "canonical_url": "http:\/\/default\/taxonomy\/term\/17"
            }
        }
    ]
}